[
  {
    "_id": "1",
    "category": "Web Design",
    "title": "HTML & CSS Fundamentals",
    "description": "Learn to build modern websites using HTML5 and CSS3.",
    "registrationStart": "2025-06-10",
    "registrationEnd": "2025-07-20",
    "rating": 4.8,
    "videoTime": "6h 30m",
    "lectures": 45,
    "image": "https://i.ibb.co/sdWsXD6X/08-Dg-NLq-CM.jpg",
    "status": "approved",
    "classStartDate": "2025-06-25",
    "classEndDate": "2025-08-10",
    "duration": "15 days",
    "registrationFee": 40,
    "tutorName": "John Doe"
  },
  {
    "_id": "2",
    "category": "Web Design",
    "title": "Responsive Web Design",
    "description": "Master flexbox, grid, and media queries to make responsive websites.",
    "registrationStart": "2025-06-01",
    "registrationEnd": "2025-06-12",
    "rating": 4.7,
    "videoTime": "5h 15m",
    "lectures": 36,
    "image": "https://i.ibb.co/Gvv5cDTQ/02-CLuao9-PX.jpg",
    "status": "approved",
    "classStartDate": "2025-06-25",
    "classEndDate": "2025-07-10",
    "duration": "15 days",
    "registrationFee": 0,
    "tutorName": "John Doe"
  },
  {
    "_id": "3",
    "category": "Web Design",
    "title": "Tailwind CSS Crash Course",
    "description": "Speed up your UI design with Tailwind utility classes.",
    "registrationStart": "2025-06-11",
    "registrationEnd": "2025-08-19",
    "rating": 4.6,
    "videoTime": "4h 50m",
    "lectures": 30,
    "image": "https://i.ibb.co/xSNQk69f/03-Jif-BASt-H.jpg",
    "status": "approved",
    "classStartDate": "2025-06-25",
    "classEndDate": "2025-07-10",
    "duration": "15 days",
    "registrationFee": 20,
    "tutorName": "John Doe"
  },
  {
    "_id": "4",
    "category": "Web Design",
    "title": "JavaScript for Designers",
    "description": "Use JS to add interactivity to your websites.",
    "registrationStart": "2025-06-13",
    "registrationEnd": "2025-08-23",
    "rating": 4.5,
    "videoTime": "6h",
    "lectures": 40,
    "image": "https://i.ibb.co/3YfjK7Ry/11-Cg-X7q-W4-Y.jpg",
    "status": "approved",
    "classStartDate": "2025-06-25",
    "classEndDate": "2025-08-10",
    "duration": "15 days",
    "registrationFee": 0,
    "tutorName": "John Doe"
  },
  {
    "_id": "5",
    "category": "Web Design",
    "title": "Figma to HTML Conversion",
    "description": "Turn Figma UI designs into fully functional HTML pages.",
    "registrationStart": "2025-06-15",
    "registrationEnd": "2025-06-25",
    "rating": 4.9,
    "videoTime": "3h 40m",
    "lectures": 28,
    "image": "https://i.ibb.co/m5MhwKk4/12-BBA2z-Dw-G.jpg",
    "status": "approved",
    "classStartDate": "2025-06-25",
    "classEndDate": "2025-07-10",
    "duration": "15 days",
    "registrationFee": 80,
    "tutorName": "John Doe"
  },
  {
    "_id": "6",
    "category": "Web Design",
    "title": "CSS Animations & Transitions",
    "description": "Make websites engaging with smooth animations.",
    "registrationStart": "2025-06-18",
    "registrationEnd": "2025-09-28",
    "rating": 4.7,
    "videoTime": "4h 10m",
    "lectures": 33,
    "image": "https://i.ibb.co/JjGk9XDJ/07-d-Jzvunm-Q.jpg",
    "status": "approved",
    "classStartDate": "2025-06-25",
    "classEndDate": "2025-07-10",
    "duration": "15 days",
    "registrationFee": 90,
    "tutorName": "John Doe"
  },
  {
    "_id": "7",
    "category": "Web Design",
    "title": "Bootstrap 5 Masterclass",
    "description": "Create responsive layouts using Bootstrap components.",
    "registrationStart": "2025-06-08",
    "registrationEnd": "2025-09-18",
    "rating": 4.5,
    "videoTime": "5h 20m",
    "lectures": 38,
    "image": "https://i.ibb.co/jtsSwbP/09-wyx1hh-Tj-1.jpg",
    "status": "approved",
    "classStartDate": "2025-06-25",
    "classEndDate": "2025-07-10",
    "duration": "15 days",
    "registrationFee": 40,
    "tutorName": "John Doe"
  },
  {
    "_id": "8",
    "category": "Web Design",
    "title": "Modern Web UI/UX Design",
    "description": "Learn color theory, typography, and layout design.",
    "registrationStart": "2025-06-09",
    "registrationEnd": "2025-06-19",
    "rating": 4.9,
    "videoTime": "7h 15m",
    "lectures": 50,
    "image": "https://i.ibb.co/WvcYYSJ5/04-RS5-CBO1g-1.jpg",
    "status": "approved",
    "classStartDate": "2025-06-25",
    "classEndDate": "2025-07-10",
    "duration": "15 days",
    "registrationFee": 0,
    "tutorName": "John Doe"
  },
  {
    "_id": "9",
    "category": "Development",
    "title": "React Basics",
    "description": "Learn React components, hooks, and state management.",
    "registrationStart": "2025-06-10",
    "registrationEnd": "2025-09-20",
    "rating": 4.8,
    "videoTime": "6h 45m",
    "lectures": 42,
    "image": "https://i.ibb.co/JjGk9XDJ/07-d-Jzvunm-Q.jpg",
    "status": "approved",
    "classStartDate": "2025-06-25",
    "classEndDate": "2025-08-10",
    "duration": "15 days",
    "registrationFee": 60,
    "tutorName": "John Doe"
  },
  {
    "_id": "10",
    "category": "Development",
    "title": "Node.js & Express Fundamentals",
    "description": "Build REST APIs with Node and Express.",
    "registrationStart": "2025-06-12",
    "registrationEnd": "2025-09-22",
    "rating": 4.6,
    "videoTime": "5h 30m",
    "lectures": 35,
    "image": "https://i.ibb.co/sdWsXD6X/08-Dg-NLq-CM.jpg",
    "status": "approved",
    "classStartDate": "2025-06-25",
    "classEndDate": "2025-09-10",
    "duration": "15 days",
    "registrationFee": 60,
    "tutorName": "John Doe"
  },
  {
    "_id": "11",
    "category": "Development",
    "title": "MongoDB for Beginners",
    "description": "Learn NoSQL with MongoDB and integrate with Node.",
    "registrationStart": "2025-06-18",
    "registrationEnd": "2025-09-28",
    "rating": 4.7,
    "videoTime": "4h 25m",
    "lectures": 29,
    "image": "https://i.ibb.co/m5MhwKk4/12-BBA2z-Dw-G.jpg",
    "status": "approved",
    "classStartDate": "2025-06-25",
    "classEndDate": "2025-07-10",
    "duration": "15 days",
    "registrationFee": 0,
    "tutorName": "John Doe"
  },
  {
    "_id": "12",
    "category": "Graphics Design",
    "title": "Adobe Photoshop Basics",
    "description": "Edit photos and design graphics like a pro.",
    "registrationStart": "2025-06-07",
    "registrationEnd": "2025-09-17",
    "rating": 4.7,
    "videoTime": "5h",
    "lectures": 32,
    "image": "https://i.ibb.co/m5MhwKk4/12-BBA2z-Dw-G.jpg",
    "status": "approved",
    "classStartDate": "2025-06-25",
    "classEndDate": "2025-09-10",
    "duration": "15 days",
    "registrationFee": 50,
    "tutorName": "John Doe"
  },
  {
    "_id": "13",
    "category": "Graphics Design",
    "title": "Illustrator for Beginners",
    "description": "Create logos, icons, and vector graphics.",
    "registrationStart": "2025-06-06",
    "registrationEnd": "2025-09-16",
    "rating": 4.6,
    "videoTime": "4h 30m",
    "lectures": 30,
    "image": "https://i.ibb.co/sdWsXD6X/08-Dg-NLq-CM.jpg",
    "status": "approved",
    "classStartDate": "2025-06-25",
    "classEndDate": "2025-07-10",
    "duration": "15 days",
    "registrationFee": 70,
    "tutorName": "John Doe"
  },
  {
    "_id": "14",
    "category": "Graphics Design",
    "title": "Canva Design Essentials",
    "description": "Make social media designs using Canva.",
    "registrationStart": "2025-06-11",
    "registrationEnd": "2025-09-21",
    "rating": 4.5,
    "videoTime": "3h 20m",
    "lectures": 22,
    "image": "https://i.ibb.co/WvcYYSJ5/04-RS5-CBO1g-1.jpg",
    "status": "approved",
    "classStartDate": "2025-06-25",
    "classEndDate": "2025-09-10",
    "duration": "15 days",
    "registrationFee": 0,
    "tutorName": "John Doe"
  },
  {
    "_id": "15",
    "category": "Marketing",
    "title": "Digital Marketing 101",
    "description": "Understand SEO, SEM, and social media marketing.",
    "registrationStart": "2025-06-12",
    "registrationEnd": "2025-06-22",
    "rating": 4.7,
    "videoTime": "6h 10m",
    "lectures": 35,
    "image": "https://i.ibb.co/3YfjK7Ry/11-Cg-X7q-W4-Y.jpg",
    "status": "approved",
    "classStartDate": "2025-06-25",
    "classEndDate": "2025-07-10",
    "duration": "15 days",
    "registrationFee": 60,
    "tutorName": "John Doe"
  },
  {
    "_id": "16",
    "category": "Marketing",
    "title": "Email Marketing Strategies",
    "description": "Build engaging campaigns with high conversion.",
    "registrationStart": "2025-06-14",
    "registrationEnd": "2025-09-24",
    "rating": 4.5,
    "videoTime": "3h 45m",
    "lectures": 26,
    "image": "https://i.ibb.co/jtsSwbP/09-wyx1hh-Tj-1.jpg",
    "status": "approved",
    "classStartDate": "2025-06-25",
    "classEndDate": "2025-07-10",
    "duration": "15 days",
    "registrationFee": 80,
    "tutorName": "John Doe"
  },
  {
    "_id": "17",
    "category": "Finance",
    "title": "Personal Finance Basics",
    "description": "Learn how to budget, save, and invest wisely.",
    "registrationStart": "2025-06-13",
    "registrationEnd": "2025-09-23",
    "rating": 4.6,
    "videoTime": "4h 15m",
    "lectures": 28,
    "image": "https://i.ibb.co/xSNQk69f/03-Jif-BASt-H.jpg",
    "status": "approved",
    "classStartDate": "2025-06-25",
    "classEndDate": "2025-07-10",
    "duration": "15 days",
    "registrationFee": 0,
    "tutorName": "John Doe"
  },
  {
    "_id": "18",
    "category": "Finance",
    "title": "Cryptocurrency Explained",
    "description": "Understand blockchain, bitcoin, and altcoins.",
    "registrationStart": "2025-06-16",
    "registrationEnd": "2025-06-26",
    "rating": 4.4,
    "videoTime": "3h 30m",
    "lectures": 25,
    "image": "https://i.ibb.co/sdWsXD6X/08-Dg-NLq-CM.jpg",
    "status": "approved",
    "classStartDate": "2025-06-25",
    "classEndDate": "2025-07-10",
    "duration": "15 days",
    "registrationFee": 50,
    "tutorName": "John Doe"
  }
]
